README.rst
setup.py
gunicorn_service/__init__.py
gunicorn_service/guni_service.py
gunicorn_service.egg-info/PKG-INFO
gunicorn_service.egg-info/SOURCES.txt
gunicorn_service.egg-info/dependency_links.txt
gunicorn_service.egg-info/top_level.txt