Metadata-Version: 1.1
Name: gunicorn-service
Version: 0.0.1
Summary: let gunicorn easy install as a service with pure python :>
Home-page: https://github.com/maxi119/gunicorn_service
Author: MaxiL
Author-email: maxil@interserv.com.tw
License: UNKNOWN
Download-URL: https://github.com/maxi119/gunicorn_service
Keywords: gunicorn service
Platform: UNKNOWN
Classifier: Development Status :: 1 - Planning
Classifier: Intended Audience :: Developers
Classifier: License :: OSI Approved :: Python Software Foundation License
Classifier: Programming Language :: Python
Classifier: Topic :: Software Development :: Libraries :: Python Modules
